[{"authorAvatar":"../images/default-avatar.jpg","authorName":"Ivan","contentSummary":"normal function function sayHello(firstName, lastName) { return `hello ${firstName} ${lastName}`; } function expression ...","coverImageUrl":"../programing/javascript/../../images/JavaScript_logo_2.png","creationDate":"10 Mar 2021","creationTime":"10 Mar 2021 20:12:27","isDraft":false,"isUnlisted":false,"lastModifiedDate":"10 Mar 2021","lastModifiedTime":"10 Mar 2021 20:43:04","outputPathRelativeToRoot":"programing/javascript/6-ways-to-declare-js-function.html","readingTime":"33 SEC READ","thumbnailUrl":"../programing/javascript/../../images/JavaScript_logo_2.png","title":"6 ways to declare js function"}]